cli/__init__.py
cli/tripkit_cli.py
cli/runners/__init__.py
cli/runners/itinerum.py
cli/runners/qstarz.py
itinerum_tripkit_cli-0.0.11.dist-info/LICENSE
itinerum_tripkit_cli-0.0.11.dist-info/METADATA
itinerum_tripkit_cli-0.0.11.dist-info/WHEEL
itinerum_tripkit_cli-0.0.11.dist-info/entry_points.txt
itinerum_tripkit_cli-0.0.11.dist-info/top_level.txt
itinerum_tripkit_cli-0.0.11.dist-info/RECORD
