Metadata-Version: 2.1
Name: itinerum-tripkit-cli
Version: 0.0.11
Summary: A command-line interface for running the itinerum-tripkit library
Home-page: https://github.com/TRIP-Lab/itinerum-tripkit-cli
Author: Kyle Fitzsimmons
Author-email: kafitz22@gmail.com
License: UNKNOWN
Platform: UNKNOWN
Classifier: Programming Language :: Python :: 3
Classifier: License :: OSI Approved :: GNU General Public License v3 (GPLv3)
Classifier: Operating System :: OS Independent
Requires-Python: >=3.6
Requires-Dist: Click
Requires-Dist: itinerum-tripkit (==0.0.16)
